flask_wechat_share/__init__.py
flask_wechat_share/templates/__wechat_share__.html
flask_wechat_share/templates/__wechat_share_ajax__.html
flask_wechat_share/templates/__wechat_share_js__.html
flask_wechat_share-0.0.8.dist-info/LICENSE
flask_wechat_share-0.0.8.dist-info/WHEEL
flask_wechat_share-0.0.8.dist-info/METADATA
flask_wechat_share-0.0.8.dist-info/RECORD
